hoymiles_wifi/__init__.py
hoymiles_wifi/__main__.py
hoymiles_wifi/const.py
hoymiles_wifi/crypt_util.py
hoymiles_wifi/dtu.py
hoymiles_wifi/hoymiles.py
hoymiles_wifi/utils.py
hoymiles_wifi/protobuf/APPHeartbeatPB_pb2.py
hoymiles_wifi/protobuf/APPInfomationData_pb2.py
hoymiles_wifi/protobuf/AlarmData_pb2.py
hoymiles_wifi/protobuf/AppGetHistED_pb2.py
hoymiles_wifi/protobuf/AppGetHistPower_pb2.py
hoymiles_wifi/protobuf/AutoSearch_pb2.py
hoymiles_wifi/protobuf/CommandPB_pb2.py
hoymiles_wifi/protobuf/DevConfig_pb2.py
hoymiles_wifi/protobuf/ESData_pb2.py
hoymiles_wifi/protobuf/ESRegPB_pb2.py
hoymiles_wifi/protobuf/ESUserSet_pb2.py
hoymiles_wifi/protobuf/EventData_pb2.py
hoymiles_wifi/protobuf/GPSTData_pb2.py
hoymiles_wifi/protobuf/GWInfo_pb2.py
hoymiles_wifi/protobuf/GWNetInfo_pb2.py
hoymiles_wifi/protobuf/GetConfig_pb2.py
hoymiles_wifi/protobuf/InfomationData_pb2.py
hoymiles_wifi/protobuf/NetworkInfo_pb2.py
hoymiles_wifi/protobuf/RealDataNew_pb2.py
hoymiles_wifi/protobuf/RealData_pb2.py
hoymiles_wifi/protobuf/SetConfig_pb2.py
hoymiles_wifi/protobuf/WarnData_pb2.py
hoymiles_wifi/protobuf/__init__.py
hoymiles_wifi-0.5.3.dist-info/licenses/LICENSE
hoymiles_wifi-0.5.3.dist-info/METADATA
hoymiles_wifi-0.5.3.dist-info/WHEEL
hoymiles_wifi-0.5.3.dist-info/entry_points.txt
hoymiles_wifi-0.5.3.dist-info/top_level.txt
hoymiles_wifi-0.5.3.dist-info/RECORD
