Metadata-Version: 2.4
Name: hoymiles-wifi
Version: 0.5.3
Summary: Library to communicate with Hoymiles DTUs and HMS WiFi enabled microinverters via protobuf.
Author: suaveolent
License-Expression: MIT
Project-URL: Homepage, https://github.com/suaveolent/hoymiles-wifi
Project-URL: Issues, https://github.com/suaveolent/hoymiles-wifi/issues
Classifier: Programming Language :: Python :: 3
Classifier: Operating System :: OS Independent
Requires-Python: >=3.9
License-File: LICENSE
Requires-Dist: protobuf>=5.29.3
Requires-Dist: crcmod>=1.7
Requires-Dist: cryptography>=39.0.1
Dynamic: license-file
